outlines_core/__init__.py
outlines_core/_json_schema.py
outlines_core/kernels/__init__.py
outlines_core/kernels/mlx.py
outlines_core/kernels/numpy.py
outlines_core/kernels/torch.py
outlines_core/outlines_core.cpython-310-darwin.so
outlines_core-0.2.14.dist-info/METADATA
outlines_core-0.2.14.dist-info/WHEEL
outlines_core-0.2.14.dist-info/licenses/LICENSE
outlines_core-0.2.14.dist-info/RECORD
