Metadata-Version: 2.4
Name: outlines_core
Version: 0.2.14
Classifier: Development Status :: 5 - Production/Stable
Classifier: Intended Audience :: Developers
Classifier: Intended Audience :: Information Technology
Classifier: Intended Audience :: Science/Research
Classifier: Operating System :: OS Independent
Classifier: Programming Language :: Python :: 3
Classifier: Topic :: Scientific/Engineering :: Artificial Intelligence
Requires-Dist: pre-commit ; extra == 'test'
Requires-Dist: pydantic ; extra == 'test'
Requires-Dist: pytest ; extra == 'test'
Requires-Dist: pytest-benchmark ; extra == 'test'
Requires-Dist: pytest-cov ; extra == 'test'
Requires-Dist: pytest-mock ; extra == 'test'
Requires-Dist: coverage[toml]>=5.1 ; extra == 'test'
Requires-Dist: diff-cover ; extra == 'test'
Requires-Dist: numpy ; extra == 'test'
Requires-Dist: torch ; extra == 'test'
Requires-Dist: numba ; extra == 'test'
Requires-Dist: scipy ; extra == 'test'
Requires-Dist: asv ; extra == 'test'
Requires-Dist: psutil ; extra == 'test'
Requires-Dist: maturin[patchelf] ; extra == 'test'
Provides-Extra: test
License-File: LICENSE
Summary: Structured Text Generation in Rust
Keywords: machine learning,deep learning,language models,structured generation
Author: Outlines Developers
License: Apache-2.0
Requires-Python: >=3.8
Project-URL: documentation, https://dottxt-ai.github.io/outlines-core/
Project-URL: homepage, https://github.com/dottxt-ai/outlines-core
Project-URL: repository, https://github.com/dottxt-ai/outlines-core
